{
  "data": [
    {
      "username":"admin",
      "password":"12345",
      "name":"name",
      "surname":"surname",
      "email":"admin@aueb.gr",
      "address":{"area":"area1", "road":"road1"},
      "phone":[21022222,69322222]
    },
    {
      "username":"user1",
      "password":"12345",
      "name":"name1",
      "surname":"surname1",
      "email":"user1@aueb.gr",
      "address":{"area":"area2", "road":"road2"},
      "phone":[21033333,69333333]
    },
    {
      "username":"user2",
      "password":"12345",
      "name":"name2",
      "surname":"surname2",
      "email":"user2@aueb.gr",
      "address":{"area":"area3", "road":"road3"},
      "phone":[21033333,69344444]
    },
    {
      "username":"user3",
      "password":"12345",
      "name":"name3",
      "surname":"surname3",
      "email":"user3@aueb.gr",
      "address":{"area":"area2", "road":"road2"},
      "phone":[21044444,69344444]
    },
    {
      "username":"user4",
      "password":"12345",
      "name":"name4",
      "surname":"surname4",
      "email":"user4@aueb.gr",
      "address":{"area":"area4", "road":"road4"},
      "phone":[21044444,69344444]
    }
  ] 
}